{
    "parent": "genshinstrument_lm:genshin_instruments/master",

    "display": {
        "icon": {
            "item": "genshinstrument_lm:shamisen"
        },
        "hidden": false,

        "title": {
            "translate": "genshinstrument_lm.advancements.main.japanese.title"
        },
        "description": {
            "translate": "genshinstrument_lm.advancements.main.japanese.description"
        },

        "frame": "goal"
    },

    "criteria": {
        "koto_played": {
            "trigger": "genshinstrument_lm_instrument_played",

            "conditions": {
                "instrument": {
                    "items": ["genshinstrument_lm:koto"]
                }
            }
        },
        "pipa_played": {
            "trigger": "genshinstrument_lm_instrument_played",

            "conditions": {
                "instrument": {
                    "items": ["genshinstrument_lm:pipa"]
                }
            }
        },
        "shamisen_played": {
            "trigger": "genshinstrument_lm_instrument_played",

            "conditions": {
                "instrument": {
                    "items": ["genshinstrument_lm:shamisen"]
                }
            }
        }
    },

    "requirements": [
        ["koto_played"],
        ["pipa_played"],
        ["shamisen_played"]
    ]
}