{
    "parent": "genshinstrument_lm:genshin_instruments/floral_zither",

    "display": {
        "icon": {
            "item": "genshinstrument_lm:glorious_drum"
        },

        "title": {
            "translate": "genshinstrument_lm.advancements.main.glorious_drum.title"
        },
        "description": {
            "translate": "genshinstrument_lm.advancements.main.glorious_drum.description"
        }
    },

    "criteria": {
        "instrument_played": {
            "trigger": "genshinstrument_lm_instrument_played",

            "conditions": {
                "instrument": {
                    "items": ["genshinstrument_lm:glorious_drum"]
                }
            }
        }
    },

    "requirements": [
        ["instrument_played"]
    ]
}